explainiverse/__init__.py
explainiverse/adapters/__init__.py
explainiverse/adapters/base_adapter.py
explainiverse/adapters/sklearn_adapter.py
explainiverse/core/__init__.py
explainiverse/core/explainer.py
explainiverse/core/explanation.py
explainiverse/engine/__init__.py
explainiverse/engine/suite.py
explainiverse/evaluation/__init__.py
explainiverse/evaluation/metrics.py
explainiverse/explainers/__init__.py
explainiverse/explainers/attribution/__init__.py
explainiverse/explainers/attribution/lime_wrapper.py
explainiverse/explainers/attribution/shap_wrapper.py
explainiverse-0.1.1a1.dist-info/LICENSE
explainiverse-0.1.1a1.dist-info/METADATA
explainiverse-0.1.1a1.dist-info/WHEEL
explainiverse-0.1.1a1.dist-info/RECORD
