Metadata-Version: 2.1
Name: explainiverse
Version: 0.1.1a1
Summary: Unified, extensible explainability framework supporting LIME, SHAP, and custom adapters
Home-page: https://github.com/jemsbhai/explainiverse
License: MIT
Author: Muntaser Syed
Author-email: jemsbhai@gmail.com
Requires-Python: >=3.10,<3.13
Classifier: License :: OSI Approved :: MIT License
Classifier: Programming Language :: Python :: 3
Classifier: Programming Language :: Python :: 3.10
Classifier: Programming Language :: Python :: 3.11
Classifier: Programming Language :: Python :: 3.12
Requires-Dist: lime (>=0.2.0.1,<0.3.0.0)
Requires-Dist: numpy (==1.24.4)
Requires-Dist: scikit-learn (>=1.1,<1.4)
Requires-Dist: shap (>=0.48.0,<0.49.0)
Requires-Dist: xgboost (>=3.0.2,<4.0.0)
Project-URL: Repository, https://github.com/jemsbhai/explainiverse
